whizkers.py
whizkers-1.1.0.dist-info/DESCRIPTION.rst
whizkers-1.1.0.dist-info/METADATA
whizkers-1.1.0.dist-info/RECORD
whizkers-1.1.0.dist-info/WHEEL
whizkers-1.1.0.dist-info/entry_points.txt
whizkers-1.1.0.dist-info/metadata.json
whizkers-1.1.0.dist-info/top_level.txt
