Metadata-Version: 2.0
Name: whizkers
Version: 1.1.0
Summary: Mustache + YAML based config templater.
Home-page: https://github.com/metakirby5/whizkers
Author: Ethan Chan
Author-email: metakirby5@gmail.com
License: MIT
Keywords: whizkers config templater mustache yaml
Platform: UNKNOWN
Classifier: Development Status :: 4 - Beta
Classifier: Environment :: Console
Classifier: Intended Audience :: End Users/Desktop
Classifier: Topic :: Utilities
Classifier: License :: OSI Approved :: MIT License
Classifier: Natural Language :: English
Classifier: Operating System :: POSIX :: Linux
Classifier: Programming Language :: Python :: 2
Classifier: Programming Language :: Python :: 3
Requires-Dist: PyYAML
Requires-Dist: argcomplete
Requires-Dist: colorlog
Requires-Dist: pystache
Requires-Dist: termcolor
Requires-Dist: watchdog
